ModellingArch/Model.py
ModellingArch/__init__.py
ModellingArch/__main__.py
ModellingArch-0.0.8.dist-info/LICENSE
ModellingArch-0.0.8.dist-info/METADATA
ModellingArch-0.0.8.dist-info/WHEEL
ModellingArch-0.0.8.dist-info/top_level.txt
ModellingArch-0.0.8.dist-info/RECORD
