Metadata-Version: 2.1
Name: ModellingArch
Version: 0.0.8
Summary: A package for modelling the photocycle of arch
Home-page: https://github.com/MikaZeilstra/ModellingArch
Author: MikaZ
Author-email: M.J.Zeilstra@student.tudelft.nl
License: UNKNOWN
Platform: UNKNOWN
Classifier: Programming Language :: Python :: 3
Classifier: License :: OSI Approved :: MIT License
Classifier: Operating System :: OS Independent
Requires-Python: >=3.9
Requires-Dist: matplotlib (==3.3.3)
Requires-Dist: sympy (==1.7.1)
Requires-Dist: scipy (==1.5.4)
